integrationos_sdk/__init__.py
integrationos_sdk/client.py
integrationos_sdk-0.1.1.dist-info/LICENSE
integrationos_sdk-0.1.1.dist-info/METADATA
integrationos_sdk-0.1.1.dist-info/WHEEL
integrationos_sdk-0.1.1.dist-info/top_level.txt
integrationos_sdk-0.1.1.dist-info/RECORD
