Metadata-Version: 2.1
Name: integrationos_sdk
Version: 0.1.1
Summary: Python SDK for IntegrationOS API
Author-email: Moe Katib <moe@integrationos.com>
Project-URL: Homepage, https://github.com/integration-os/unified-python-sdk
Keywords: integrationos,api,sdk
Classifier: License :: OSI Approved :: MIT License
Classifier: Programming Language :: Python
Classifier: Programming Language :: Python :: 3
Requires-Python: >=3.7
License-File: LICENSE
Requires-Dist: requests>=2.25.1
Provides-Extra: dev
Requires-Dist: pytest; extra == "dev"
